nllw/__init__.py
nllw/core.py
nllw/languages.py
nllw/test_strings.py
nllw/timed_text.py
nllw/translation.py
nllw-0.1.2.dist-info/METADATA
nllw-0.1.2.dist-info/WHEEL
nllw-0.1.2.dist-info/top_level.txt
nllw-0.1.2.dist-info/RECORD
