Metadata-Version: 2.4
Name: nllw
Version: 0.1.2
Summary: Simultaneous Machine Translation (SimulMT) with NLLB model optimization
Author: Quentin Fuxa
License: MIT
Project-URL: Homepage, https://github.com/QuentinFuxa/NoLanguageLeftWaiting
Keywords: machine-translation,simultaneous-translation,nllb,streaming,nlp,transformers,ai
Classifier: Development Status :: 4 - Beta
Classifier: Intended Audience :: Developers
Classifier: License :: OSI Approved :: MIT License
Classifier: Programming Language :: Python :: 3.9
Classifier: Programming Language :: Python :: 3.10
Classifier: Programming Language :: Python :: 3.11
Classifier: Programming Language :: Python :: 3.12
Classifier: Programming Language :: Python :: 3.13
Classifier: Programming Language :: Python :: 3.14
Classifier: Programming Language :: Python :: 3.15
Classifier: Topic :: Scientific/Engineering :: Artificial Intelligence
Classifier: Topic :: Multimedia :: Sound/Audio :: Speech
Requires-Python: >=3.8
Requires-Dist: torch>=1.10.0
Requires-Dist: transformers>=4.30.0
Provides-Extra: ctranslate2
Requires-Dist: ctranslate2>=3.16.0; extra == "ctranslate2"
Provides-Extra: demo
Requires-Dist: textual>=0.40.0; extra == "demo"
Requires-Dist: bertviz>=1.4.1; extra == "demo"
Requires-Dist: transformers>4.57; extra == "demo"
